munin2smartphone/__init__.py
munin2smartphone/config.py
munin2smartphone/datastore.py
munin2smartphone/entrypoints.py
munin2smartphone/exceptions.py
munin2smartphone/point.png
munin2smartphone/server.py
munin2smartphone/templates/report.html.jinja2
munin2smartphone/utils.py
munin2smartphone/widget.py
munin2smartphone-0.0.4.dist-info/entry_points.txt
munin2smartphone-0.0.4.dist-info/LICENSE
munin2smartphone-0.0.4.dist-info/LICENSE_CeCILL_2.1.txt
munin2smartphone-0.0.4.dist-info/LICENSE_GPL_2.txt
munin2smartphone-0.0.4.dist-info/WHEEL
munin2smartphone-0.0.4.dist-info/METADATA
munin2smartphone-0.0.4.dist-info/RECORD
