Metadata-Version: 2.1
Name: munin2smartphone
Version: 0.0.4
Summary: Demilitarized HTTP server eating munin monitoring data and producing static pages that can be displayed securely (ie. without javascript), on your smartphone.
Home-page: https://framagit.org/feth/munin2smartphone
Keywords: monitoring,munin,web
Author: Feth AREZKI
Author-email: feth@majerti.fr
Requires-Python: >=3.6
Classifier: Development Status :: 3 - Alpha
Classifier: Environment :: No Input/Output (Daemon)
Classifier: Environment :: Web Environment
Classifier: Intended Audience :: Information Technology
Classifier: Intended Audience :: System Administrators
Classifier: License :: OSI Approved :: CEA CNRS Inria Logiciel Libre License, version 2.1 (CeCILL-2.1)
Classifier: License :: OSI Approved :: GNU General Public License v2 (GPLv2)
Classifier: Natural Language :: English
Classifier: Operating System :: POSIX :: Linux
Classifier: Programming Language :: Python :: 3
Classifier: Programming Language :: Python :: 3.6
Classifier: Programming Language :: Python :: 3.7
Classifier: Programming Language :: Python :: 3.8
Classifier: Topic :: System :: Monitoring
Provides-Extra: docs
Requires-Dist: PyYAML (==5.3.1)
Requires-Dist: aiohttp (==3.6.2)
Requires-Dist: coloredlogs (>=14.0,<15.0)
Requires-Dist: jinja2 (>=2.11.2,<3.0.0)
Requires-Dist: pytz (>=2020.1,<2021.0)
Requires-Dist: pyxdg (>=0.26,<0.27)
Requires-Dist: quicklogging (>=0.3,<0.4)
Requires-Dist: toml (>=0.10.1,<0.11.0)
Project-URL: Documentation, https://munin2smartphone.readthedocs.io/
Project-URL: Repository, https://framagit.org/feth/munin2smartphone.git
